pdf_watermark/__init__.py
pdf_watermark/_version.py
pdf_watermark/draw.py
pdf_watermark/font_utils.py
pdf_watermark/handler.py
pdf_watermark/options.py
pdf_watermark/utils.py
pdf_watermark/watermark.py
pdf_watermark-3.0.0.dist-info/licenses/LICENSE
pdf_watermark-3.0.0.dist-info/METADATA
pdf_watermark-3.0.0.dist-info/WHEEL
pdf_watermark-3.0.0.dist-info/entry_points.txt
pdf_watermark-3.0.0.dist-info/top_level.txt
pdf_watermark-3.0.0.dist-info/RECORD
