Metadata-Version: 2.4
Name: pdf-watermark
Version: 3.0.0
Summary: A python CLI tool to add watermarks to a PDF
Author-email: Bastien Le Chenadec <dev@lechenadec.com>
Project-URL: Homepage, https://github.com/bastienlc/pdf-watermark
Project-URL: Repository, https://github.com/bastienlc/pdf-watermark.git
Project-URL: Bug Tracker, https://github.com/bastienlc/pdf-watermark/issues
Keywords: pdf,watermark,cli
Classifier: Programming Language :: Python :: 3.11
Classifier: Operating System :: OS Independent
Requires-Python: >=3.10
License-File: LICENSE
Requires-Dist: pypdf>=3.11.0
Requires-Dist: pillow>=9.5.0
Requires-Dist: reportlab>=4.4.4
Requires-Dist: numpy>=1.25.0
Requires-Dist: click>=8.1.3
Requires-Dist: pdf2image>=1.17.0
Requires-Dist: types-reportlab>=4.4.4.20250926
Requires-Dist: dataclass-click>=1.0.4
Dynamic: license-file
